pksmart/__init__.py
pksmart/data/.DS_Store
pksmart/data/Median_mordred_values_dog_for_artificial_animal_data_mfp_mrd_model.csv
pksmart/data/Median_mordred_values_human_for_artificial_animal_data_mfp_mrd_model.csv
pksmart/data/Median_mordred_values_monkey_for_artificial_animal_data_mfp_mrd_model.csv
pksmart/data/Median_mordred_values_rat_for_artificial_animal_data_mfp_mrd_model.csv
pksmart/data/Train_data_features.csv
pksmart/data/Train_data_log_transformed.csv
pksmart/data/artificial_animal_data_mfp_mrd_humanPK_scaler.pkl
pksmart/data/artificial_animal_data_mfp_mrd_human_CL_mL_min_kg_scaler.pkl
pksmart/data/artificial_animal_data_mfp_mrd_human_VDss_L_kg_scaler.pkl
pksmart/data/artificial_animal_data_mfp_mrd_human_fup_scaler.pkl
pksmart/data/artificial_animal_data_mfp_mrd_human_mrt_scaler.pkl
pksmart/data/artificial_animal_data_mfp_mrd_human_thalf_scaler.pkl
pksmart/data/features_mfp_mordred_animal_artificial_human_modelcolumns.txt
pksmart/data/features_mfp_mordred_columns_dog_model.txt
pksmart/data/features_mfp_mordred_columns_human.txt
pksmart/data/features_mfp_mordred_columns_monkey_model.txt
pksmart/data/features_mfp_mordred_columns_rat_model.txt
pksmart/data/features_mordred_columns_human.txt
pksmart/data/folderror_human_CL_mL_min_kg_generator.sav
pksmart/data/folderror_human_VDss_L_kg_generator.sav
pksmart/data/folderror_human_fup_generator.sav
pksmart/data/folderror_human_mrt_generator.sav
pksmart/data/folderror_human_thalf_generator.sav
pksmart/data/human_trainingdata_5nn_similarity_all_compounds_endpoint_wise.csv
pksmart/data/log_dog_CL_mL_min_kg_model_FINAL.sav
pksmart/data/log_dog_VDss_L_kg_model_FINAL.sav
pksmart/data/log_dog_fup_model_FINAL.sav
pksmart/data/log_human_CL_mL_min_kg_withanimaldata_artificial_model_FINAL.sav
pksmart/data/log_human_VDss_L_kg_withanimaldata_artificial_model_FINAL.sav
pksmart/data/log_human_fup_withanimaldata_artificial_model_FINAL.sav
pksmart/data/log_human_mrt_withanimaldata_artificial_model_FINAL.sav
pksmart-3.0.1.dist-info/METADATA
pksmart-3.0.1.dist-info/WHEEL
pksmart-3.0.1.dist-info/entry_points.txt
pksmart-3.0.1.dist-info/RECORD
