Metadata-Version: 2.1
Name: pksmart
Version: 3.0.1
Summary: PKSmart: An Open-Source Computational Model to Predict in vivo Pharmacokinetics of Small Molecules
Author: Manas Mahale
Requires-Python: >=3.10,<3.12
Classifier: Programming Language :: Python :: 3
Classifier: Programming Language :: Python :: 3.10
Classifier: Programming Language :: Python :: 3.11
Requires-Dist: dimorphite-dl (==2.0.1)
Requires-Dist: loguru (>=0.7.2,<0.8.0)
Requires-Dist: mordred (==1.2.0)
Requires-Dist: numpy (==1.23.5)
Requires-Dist: pandas (==1.5.2)
Requires-Dist: rdkit (>=2023.3.3,<2024.0.0)
Requires-Dist: scikit-learn (==1.2.1)
Requires-Dist: tabulate (>=0.9.0,<0.10.0)
